{"nodes": [{"id": "src_components_dashboard_driverstandingscard_tsx", "label": "DriverStandingsCard.tsx", "file_type": "code", "source_file": "src\\components\\dashboard\\DriverStandingsCard.tsx", "source_location": "L1"}, {"id": "driverstandingscard_skeletonrow", "label": "SkeletonRow()", "file_type": "code", "source_file": "src\\components\\dashboard\\DriverStandingsCard.tsx", "source_location": "L14"}, {"id": "driverstandingscard_driverstandingscard", "label": "DriverStandingsCard()", "file_type": "code", "source_file": "src\\components\\dashboard\\DriverStandingsCard.tsx", "source_location": "L27"}], "edges": [{"source": "src_components_dashboard_driverstandingscard_tsx", "target": "framer_motion", "relation": "imports_from", "confidence": "EXTRACTED", "source_file": "src\\components\\dashboard\\DriverStandingsCard.tsx", "source_location": "L3", "weight": 1.0}, {"source": "src_components_dashboard_driverstandingscard_tsx", "target": "f1", "relation": "imports_from", "confidence": "EXTRACTED", "source_file": "src\\components\\dashboard\\DriverStandingsCard.tsx", "source_location": "L4", "weight": 1.0}, {"source": "src_components_dashboard_driverstandingscard_tsx", "target": "utils", "relation": "imports_from", "confidence": "EXTRACTED", "source_file": "src\\components\\dashboard\\DriverStandingsCard.tsx", "source_location": "L5", "weight": 1.0}, {"source": "src_components_dashboard_driverstandingscard_tsx", "target": "lucide_react", "relation": "imports_from", "confidence": "EXTRACTED", "source_file": "src\\components\\dashboard\\DriverStandingsCard.tsx", "source_location": "L6", "weight": 1.0}, {"source": "src_components_dashboard_driverstandingscard_tsx", "target": "driverstandingscard_skeletonrow", "relation": "contains", "confidence": "EXTRACTED", "source_file": "src\\components\\dashboard\\DriverStandingsCard.tsx", "source_location": "L14", "weight": 1.0}, {"source": "src_components_dashboard_driverstandingscard_tsx", "target": "driverstandingscard_driverstandingscard", "relation": "contains", "confidence": "EXTRACTED", "source_file": "src\\components\\dashboard\\DriverStandingsCard.tsx", "source_location": "L27", "weight": 1.0}], "raw_calls": []}