{"nodes": [{"id": "pitwallpro", "label": "Pit Wall Pro", "file_type": "document", "source_file": "README.md", "source_location": null, "source_url": null, "captured_at": null, "author": null, "contributor": null}, {"id": "frontend_framework", "label": "Next.js 15", "file_type": "document", "source_file": "README.md", "source_location": null, "source_url": null, "captured_at": null, "author": null, "contributor": null}, {"id": "backend_framework", "label": "FastAPI", "file_type": "document", "source_file": "README.md", "source_location": null, "source_url": null, "captured_at": null, "author": null, "contributor": null}, {"id": "telemetry_library", "label": "Fast-F1", "file_type": "document", "source_file": "README.md", "source_location": null, "source_url": null, "captured_at": null, "author": null, "contributor": null}, {"id": "ai_engine", "label": "Google Generative AI", "file_type": "document", "source_file": "README.md", "source_location": null, "source_url": null, "captured_at": null, "author": null, "contributor": null}, {"id": "state_management", "label": "Zustand", "file_type": "document", "source_file": "README.md", "source_location": null, "source_url": null, "captured_at": null, "author": null, "contributor": null}, {"id": "data_visualization", "label": "Recharts", "file_type": "document", "source_file": "README.md", "source_location": null, "source_url": null, "captured_at": null, "author": null, "contributor": null}, {"id": "animation_library", "label": "Framer Motion", "file_type": "document", "source_file": "README.md", "source_location": null, "source_url": null, "captured_at": null, "author": null, "contributor": null}, {"id": "styling_framework", "label": "Tailwind CSS", "file_type": "document", "source_file": "README.md", "source_location": null, "source_url": null, "captured_at": null, "author": null, "contributor": null}, {"id": "predictive_modeling", "label": "Predictive Modeling", "file_type": "document", "source_file": "README.md", "source_location": null, "source_url": null, "captured_at": null, "author": null, "contributor": null}, {"id": "session_analysis", "label": "Session Analysis", "file_type": "document", "source_file": "README.md", "source_location": null, "source_url": null, "captured_at": null, "author": null, "contributor": null}, {"id": "real_time_telemetry", "label": "Real-time Telemetry", "file_type": "document", "source_file": "README.md", "source_location": null, "source_url": null, "captured_at": null, "author": null, "contributor": null}, {"id": "ai_strategy_engine", "label": "AI Strategy Engine", "file_type": "document", "source_file": "README.md", "source_location": null, "source_url": null, "captured_at": null, "author": null, "contributor": null}], "edges": [{"source": "pitwallpro", "target": "real_time_telemetry", "relation": "references", "confidence": "EXTRACTED", "confidence_score": 1.0, "source_file": "README.md", "source_location": null, "weight": 1.0}, {"source": "pitwallpro", "target": "ai_strategy_engine", "relation": "references", "confidence": "EXTRACTED", "confidence_score": 1.0, "source_file": "README.md", "source_location": null, "weight": 1.0}, {"source": "pitwallpro", "target": "predictive_modeling", "relation": "references", "confidence": "EXTRACTED", "confidence_score": 1.0, "source_file": "README.md", "source_location": null, "weight": 1.0}, {"source": "pitwallpro", "target": "session_analysis", "relation": "references", "confidence": "EXTRACTED", "confidence_score": 1.0, "source_file": "README.md", "source_location": null, "weight": 1.0}, {"source": "pitwallpro", "target": "frontend_framework", "relation": "implemented_with", "confidence": "EXTRACTED", "confidence_score": 1.0, "source_file": "README.md", "source_location": null, "weight": 1.0}, {"source": "pitwallpro", "target": "backend_framework", "relation": "implemented_with", "confidence": "EXTRACTED", "confidence_score": 1.0, "source_file": "README.md", "source_location": null, "weight": 1.0}, {"source": "frontend_framework", "target": "state_management", "relation": "references", "confidence": "EXTRACTED", "confidence_score": 1.0, "source_file": "README.md", "source_location": null, "weight": 1.0}, {"source": "frontend_framework", "target": "data_visualization", "relation": "references", "confidence": "EXTRACTED", "confidence_score": 1.0, "source_file": "README.md", "source_location": null, "weight": 1.0}, {"source": "frontend_framework", "target": "animation_library", "relation": "references", "confidence": "EXTRACTED", "confidence_score": 1.0, "source_file": "README.md", "source_location": null, "weight": 1.0}, {"source": "frontend_framework", "target": "styling_framework", "relation": "references", "confidence": "EXTRACTED", "confidence_score": 1.0, "source_file": "README.md", "source_location": null, "weight": 1.0}, {"source": "backend_framework", "target": "telemetry_library", "relation": "references", "confidence": "EXTRACTED", "confidence_score": 1.0, "source_file": "README.md", "source_location": null, "weight": 1.0}, {"source": "backend_framework", "target": "pandas", "relation": "references", "confidence": "EXTRACTED", "confidence_score": 1.0, "source_file": "README.md", "source_location": null, "weight": 1.0}, {"source": "ai_strategy_engine", "target": "ai_engine", "relation": "implemented_with", "confidence": "EXTRACTED", "confidence_score": 1.0, "source_file": "README.md", "source_location": null, "weight": 1.0}, {"source": "real_time_telemetry", "target": "telemetry_library", "relation": "implemented_with", "confidence": "EXTRACTED", "confidence_score": 1.0, "source_file": "README.md", "source_location": null, "weight": 1.0}, {"source": "session_analysis", "target": "data_visualization", "relation": "conceptually_related_to", "confidence": "INFERRED", "confidence_score": 0.7, "source_file": "README.md", "source_location": null, "weight": 1.0}], "hyperedges": [{"id": "frontend_tech_stack", "label": "Frontend Technology Stack", "nodes": ["frontend_framework", "state_management", "data_visualization", "animation_library", "styling_framework"], "relation": "form", "confidence": "EXTRACTED", "confidence_score": 1.0, "source_file": "README.md"}, {"id": "backend_tech_stack", "label": "Backend Technology Stack", "nodes": ["backend_framework", "telemetry_library", "pandas", "numpy"], "relation": "form", "confidence": "EXTRACTED", "confidence_score": 1.0, "source_file": "README.md"}]}